{
  "todos": [
    {
      "dates": "2021-01-29",
      "content": "asdasd",
      "done": false,
      "id": 13
    },
    {
      "dates": "2021-01-29",
      "content": "asdasd",
      "done": false,
      "id": 14
    },
    {
      "dates": "2021-01-29",
      "content": "asdasd",
      "done": false,
      "id": 15
    },
    {
      "dates": "2021-01-29",
      "content": "ㄴㅁㅇㅁㄴㅇㅁㄴㅇ",
      "done": false,
      "id": 16
    },
    {
      "dates": "2021-02-02",
      "content": "ㅁㄴㅇㅁㄴㅇ",
      "done": false,
      "id": 17
    }
  ]
}