{
  "todos": [
    {
      "dates": "2021-01-29",
      "content": "sdfsdfsdfsdfsdf",
      "done": false,
      "id": 4
    },
    {
      "dates": "2021-01-29",
      "content": "asdasdasdasd",
      "done": false,
      "id": 5
    },
    {
      "dates": "2021-01-29",
      "content": "sadsadasd",
      "done": false,
      "id": 6
    },
    {
      "dates": "2021-01-29",
      "content": "asdasdassad",
      "done": false,
      "id": 7
    },
    {
      "dates": "2021-01-29",
      "content": "ss",
      "done": true,
      "id": 8
    }
  ]
}